longmemory/__init__.py
longmemory/client.py
longmemory/exceptions.py
longmemory-0.1.0a1.dist-info/METADATA
longmemory-0.1.0a1.dist-info/WHEEL
longmemory-0.1.0a1.dist-info/top_level.txt
longmemory-0.1.0a1.dist-info/RECORD
