Metadata-Version: 2.4
Name: longmemory
Version: 0.1.0a1
Summary: Official Python client for LongMemory.io
Author-email: LongMemory Team <hello@longmemory.io>
License: MIT
Project-URL: Homepage, https://longmemory.io
Project-URL: Source, https://github.com/itsajspace/longmemory-python
Classifier: Development Status :: 4 - Beta
Classifier: Intended Audience :: Developers
Classifier: Topic :: Software Development :: Libraries :: Python Modules
Classifier: License :: OSI Approved :: MIT License
Classifier: Programming Language :: Python :: 3
Requires-Python: >=3.11
Requires-Dist: requests>=2.25.0
